{
  "syncedAt": "2026-07-21T11:30:58.374Z",
  "inventorySource": "ShipSidekick (Doral Warehouse)",
  "summary": {
    "totalUnitsAllSKUs": 303998,
    "skusInStockout": 1,
    "skusCritical": 1,
    "ordersYesterday": 3731,
    "revenueYesterday": 265004,
    "unitsYesterday": 13597,
    "preOrdersPending": 0,
    "usSplit": 93,
    "blendedROAS": 2.23,
    "adSpend": 134160.04611572158,
    "blendedSales": 298657.2900000001,
    "netRevenue": 296874.9300000001,
    "amazonRevenue": 39823.32,
    "amazonOrders": 911,
    "amazonROAS": null,
    "amazonSpend": 0
  },
  "products": [
    {
      "name": "Bio Collagen Mask",
      "sskSku": "GLOWUP-ORIGINAL-QUAS",
      "shopifySku": "QUASI-GLOWUP-OG",
      "dropship": false,
      "stock": 198729,
      "units7d": 65333,
      "unitsToday": 7195,
      "revenue7d": 2230176,
      "dailyAvg": 9333.3,
      "daysOfSupply": 21,
      "weeksOfSupply": 3,
      "reorderPoint": 559998,
      "needsReorder": true,
      "reorderQty": 912384,
      "containers": 12,
      "leadDays": 60,
      "productionDays": 20,
      "shippingDays": 40,
      "containerUnits": 76032,
      "safetyStockDays": 21,
      "status": "low",
      "orderByDays": 0
    },
    {
      "name": "Salmon PDRM Mask",
      "sskSku": "SALMON-MASK-QUAS",
      "shopifySku": "QUASI-GLOWUP-SALMON",
      "dropship": false,
      "stock": 0,
      "units7d": 10596,
      "unitsToday": 1851,
      "revenue7d": 375589,
      "dailyAvg": 1513.7,
      "daysOfSupply": 0,
      "weeksOfSupply": 0,
      "reorderPoint": 90822,
      "needsReorder": true,
      "reorderQty": 228096,
      "containers": 3,
      "leadDays": 60,
      "productionDays": 20,
      "shippingDays": 40,
      "containerUnits": 76032,
      "safetyStockDays": 21,
      "status": "stockout",
      "orderByDays": 0
    },
    {
      "name": "Neck Mask",
      "sskSku": "NECK-QUAS",
      "shopifySku": "199284415690",
      "dropship": false,
      "stock": 43600,
      "units7d": 16016,
      "unitsToday": 1375,
      "revenue7d": 622030,
      "dailyAvg": 2288,
      "daysOfSupply": 19,
      "weeksOfSupply": 2.7,
      "reorderPoint": 137280,
      "needsReorder": true,
      "reorderQty": 250000,
      "containers": 5,
      "leadDays": 60,
      "productionDays": 20,
      "shippingDays": 40,
      "containerUnits": 50000,
      "safetyStockDays": 21,
      "status": "critical",
      "orderByDays": 0
    },
    {
      "name": "Night Sealing Mask",
      "sskSku": "SEALING-OIL-QUAS",
      "shopifySku": "25341366",
      "dropship": false,
      "stock": 16865,
      "units7d": 374,
      "unitsToday": 33,
      "revenue7d": 14600,
      "dailyAvg": 53.4,
      "daysOfSupply": 316,
      "weeksOfSupply": 45.1,
      "reorderPoint": 4005,
      "needsReorder": false,
      "reorderQty": 0,
      "containers": 0,
      "leadDays": 75,
      "productionDays": 35,
      "shippingDays": 40,
      "containerUnits": 50000,
      "safetyStockDays": 21,
      "status": "healthy",
      "orderByDays": 241
    },
    {
      "name": "Chest Mask",
      "sskSku": "CHEST-QUAS",
      "shopifySku": "199284450646",
      "dropship": false,
      "stock": 44804,
      "units7d": 195,
      "unitsToday": 62,
      "revenue7d": 6653,
      "dailyAvg": 27.9,
      "daysOfSupply": 1606,
      "weeksOfSupply": 229.4,
      "reorderPoint": 1674,
      "needsReorder": false,
      "reorderQty": 0,
      "containers": 0,
      "leadDays": 60,
      "productionDays": 20,
      "shippingDays": 40,
      "containerUnits": 50000,
      "safetyStockDays": 21,
      "status": "healthy",
      "orderByDays": 1546
    },
    {
      "name": "Multi Balm Stick",
      "sskSku": "dropship",
      "dropship": true,
      "stock": "dropship",
      "units7d": 0,
      "unitsToday": 0,
      "dailyAvg": 0,
      "daysOfSupply": null,
      "reorderPoint": 0,
      "needsReorder": false,
      "reorderQty": 0,
      "status": "dropship"
    },
    {
      "name": "Eye Patches",
      "sskSku": "dropship",
      "dropship": true,
      "stock": "dropship",
      "units7d": 0,
      "unitsToday": 0,
      "dailyAvg": 0,
      "daysOfSupply": null,
      "reorderPoint": 0,
      "needsReorder": false,
      "reorderQty": 0,
      "status": "dropship"
    }
  ],
  "reorderAlerts": [
    {
      "name": "Bio Collagen Mask",
      "sskSku": "GLOWUP-ORIGINAL-QUAS",
      "stock": 198729,
      "daysLeft": 21,
      "orderQty": 912384,
      "urgency": "MEDIUM"
    },
    {
      "name": "Salmon PDRM Mask",
      "sskSku": "SALMON-MASK-QUAS",
      "stock": 0,
      "daysLeft": 0,
      "orderQty": 228096,
      "urgency": "IMMEDIATE"
    },
    {
      "name": "Neck Mask",
      "sskSku": "NECK-QUAS",
      "stock": 43600,
      "daysLeft": 19,
      "orderQty": 250000,
      "urgency": "HIGH"
    }
  ],
  "inboundContainers": [
    {
      "poNumber": "PO-001",
      "sskSku": "SALMON-MASK-QUAS",
      "productName": "Salmon PDRM Mask",
      "status": "pending",
      "qty": 76032,
      "containers": 1,
      "orderDate": "2026-06-25",
      "productionDays": 20,
      "shippingDays": 40,
      "expectedArrival": "2026-09-02",
      "notes": "Emergency PO — stockout imminent",
      "source": "manual"
    }
  ],
  "purchaseOrders": [
    {
      "poNumber": "PO-001",
      "sskSku": "SALMON-MASK-QUAS",
      "productName": "Salmon PDRM Mask",
      "status": "pending",
      "qty": 76032,
      "containers": 1,
      "orderDate": "2026-06-25",
      "productionDays": 20,
      "shippingDays": 40,
      "expectedArrival": "2026-09-02",
      "notes": "Emergency PO — stockout imminent"
    }
  ]
}